{
  "title": "Augusta County: John Scott to E. P. Smith, May 25, 1869",
  "summary": "Scott reports that he has closed his school and left Staunton. He states that he could not remain in Staunton to oversee the construction of a new schoolhouse because he was unable to raise the necessary funds.",
  "keywords": "African Americans, Education, Race Relations, Church/Religious Activity, American Civil War",
  "source_file": "api.valley.newamericanhistory.org/storage/data/papers/A7166.xml",
  "content_file": "content/p042_011.html"
}