{
  "title": "Augusta County: Samuel Franklin Carson to Unknown (Annie Harris), September 24",
  "summary": "Franklin (Samuel Franklin Carson) writes to someone, almost certainly Annie Harris, describing life in camp. He explains that his unit recently retreated across a river to Shepards Town and describes Yankee attempts to cross the river.",
  "keywords": "Battle Description, Death/Casualties, Camp Life, Troop Movement, American Civil War",
  "source_file": "api.valley.newamericanhistory.org/storage/data/papers/A3000.xml",
  "content_file": "content/p002_001.html"
}