{
  "title": "Freedmen's Bureau Records: Thomas Wholey to Orlando Brown, March 12, 1866",
  "summary": "Wholey writes in reference to property that was taken from him during the war, and which he is trying to have restored to him. He also claims to have been treated poorly by the local authorities.",
  "keywords": "Aid/Relief, Property, Military Authority, American Civil War",
  "source_file": "api.valley.newamericanhistory.org/storage/data/papers/B1225.xml",
  "content_file": "content/p024_000.html"
}