{
  "title": "Freedmen's Bureau Records: R. M. Manly to Thomas P. Jackson, October 4, 1867",
  "summary": "Manly tells Jackson that the only teacher he has available at the moment is a woman, and because the charitable societies have a shortage of teachers, it is unlikely that Jackson will find a male teacher for Staunton.",
  "keywords": "Education, Aid/Relief, Women, American Civil War",
  "source_file": "api.valley.newamericanhistory.org/storage/data/papers/B2045.xml",
  "content_file": "content/p032_020.html"
}